cellpose_napari/__init__.py
cellpose_napari/_dock_widget.py
cellpose_napari/_sample_data.py
cellpose_napari/_version.py
cellpose_napari/napari.yaml
cellpose_napari-0.2.0.dist-info/LICENSE
cellpose_napari-0.2.0.dist-info/METADATA
cellpose_napari-0.2.0.dist-info/WHEEL
cellpose_napari-0.2.0.dist-info/entry_points.txt
cellpose_napari-0.2.0.dist-info/top_level.txt
cellpose_napari-0.2.0.dist-info/RECORD
